clearskies_akeyless_custom_producer/__init__.py
clearskies_akeyless_custom_producer/endpoints/__init__.py
clearskies_akeyless_custom_producer/endpoints/no_input.py
clearskies_akeyless_custom_producer/endpoints/with_input.py
clear_skies_akeyless_custom_producer-2.0.6.dist-info/METADATA
clear_skies_akeyless_custom_producer-2.0.6.dist-info/WHEEL
clear_skies_akeyless_custom_producer-2.0.6.dist-info/licenses/LICENSE
clear_skies_akeyless_custom_producer-2.0.6.dist-info/RECORD
