Metadata-Version: 2.4
Name: clear-skies-akeyless-custom-producer
Version: 2.0.6
Summary: Endpoints for managing Akeyless Custom Producers
Project-URL: Repository, https://github.com/clearskies-py/akeyless-custom-producer
Project-URL: Issues, https://github.com/clearskies-py/akeyless-custom-producer/issues
Project-URL: Changelog, https://github.com/clearskies-py/akeyless-custom-producer/blob/main/CHANGELOG.md
Author-email: Conor Mancone <cmancone@gmail.com>
License-Expression: MIT
License-File: LICENSE
Classifier: Development Status :: 5 - Production/Stable
Classifier: Intended Audience :: Developers
Classifier: License :: OSI Approved :: MIT License
Classifier: Programming Language :: Python :: 3
Requires-Python: <4.0,>=3.11
Requires-Dist: clear-skies<3.0.0,>=2.0.0
Provides-Extra: dev
Requires-Dist: types-requests>=2.32.4; extra == 'dev'
